demo.py
setup.py
crazythursday/__init__.py
crazythursday/kfc.py
crazythursday/utils.py
another_crazy_thursday-0.9.0.dist-info/METADATA
another_crazy_thursday-0.9.0.dist-info/WHEEL
another_crazy_thursday-0.9.0.dist-info/licenses/LICENSE
another_crazy_thursday-0.9.0.dist-info/RECORD
