Metadata-Version: 2.1
Name: another-crazy-thursday
Version: 0.9.0
Summary: KFC Crazy Thursday
Project-URL: Homepage, https://github.com/lee-plus-plus/crazythursday
Project-URL: Bug Tracker, https://github.com/lee-plus-plus/crazythursday/issues
Author-email: lee <leezhuoming@qq.com>
License:                     GNU GENERAL PUBLIC LICENSE
Classifier: Programming Language :: Python :: 3
Requires-Python: >=3.4
